{
  "AnalysisType": "Porphyrin",
  "OutOfPlaneParameter": {
    "Key": "Doop (exp.)",
    "Value": 0.16079025569527744,
    "Unit": "\u00C5"
  },
  "Simulation": {
    "SimulationResult": [
      {
        "Key": "Doming",
        "Value": 0.10260754367528216,
        "Unit": "\u00C5"
      },
      {
        "Key": "Saddling",
        "Value": -0.0365340808974855,
        "Unit": "\u00C5"
      },
      {
        "Key": "Ruffling",
        "Value": 0.13092484873184135,
        "Unit": "\u00C5"
      },
      {
        "Key": "WavingX",
        "Value": 0.01914306127248935,
        "Unit": "\u00C5"
      },
      {
        "Key": "WavingY",
        "Value": 0.023795562072027713,
        "Unit": "\u00C5"
      },
      {
        "Key": "Propellering",
        "Value": 0.03712933564733299,
        "Unit": "\u00C5"
      },
      {
        "Key": "Doming2",
        "Value": -0.03764400711104815,
        "Unit": "\u00C5"
      },
      {
        "Key": "Saddling2",
        "Value": -0.011284646404544338,
        "Unit": "\u00C5"
      },
      {
        "Key": "Ruffling2",
        "Value": -0.003018052564999397,
        "Unit": "\u00C5"
      },
      {
        "Key": "WavingX2",
        "Value": -0.04369057835714836,
        "Unit": "\u00C5"
      },
      {
        "Key": "Propellering2",
        "Value": 0.0108168221322979,
        "Unit": "\u00C5"
      }
    ],
    "ConformationY": [
      -0.0417971273627276,
      -0.01699821151934021,
      -0.03585210548574318,
      0.01694234046591254,
      -0.028797246739007087,
      0.01080570294573303,
      0.050531780388995515,
      0.06192050048421262,
      0.025830432964285645,
      0.04080234613550159,
      -0.051213932503275085,
      -0.02911663625412609,
      -0.05189068995058586,
      -0.012044974329120543,
      -0.03732928878011,
      0.034450649761016215,
      -0.012843096046869912,
      0.025305024416364667,
      0.0312096602479774,
      0.024117013633759666,
      0.021740754031948133,
      0.005446008468676662,
      -0.009923491123308788,
      -0.02129538781685325,
      -0.0417971273627276
    ],
    "OutOfPlaneParameter": {
      "Key": "Doop (sim.)",
      "Value": 0.1599312251541671,
      "Unit": "\u00C5"
    },
    "SimulationResultPercentage": [
      {
        "Key": "Doming",
        "Value": 22.472649867648954,
        "Unit": " %"
      },
      {
        "Key": "Saddling",
        "Value": 8.001532624577722,
        "Unit": " %"
      },
      {
        "Key": "Ruffling",
        "Value": 28.674580631583208,
        "Unit": " %"
      },
      {
        "Key": "WavingX",
        "Value": 4.1926285140693444,
        "Unit": " %"
      },
      {
        "Key": "WavingY",
        "Value": 5.211598637824184,
        "Unit": " %"
      },
      {
        "Key": "Propellering",
        "Value": 8.131902684090218,
        "Unit": " %"
      },
      {
        "Key": "Doming2",
        "Value": 8.2446237490983,
        "Unit": " %"
      },
      {
        "Key": "Saddling2",
        "Value": 2.4715132868991874,
        "Unit": " %"
      },
      {
        "Key": "Ruffling2",
        "Value": 0.6610005087932904,
        "Unit": " %"
      },
      {
        "Key": "WavingX2",
        "Value": 9.568917009089258,
        "Unit": " %"
      },
      {
        "Key": "Propellering2",
        "Value": 2.3690524863263493,
        "Unit": " %"
      }
    ]
  },
  "Dihedrals": [
    {
      "Value": 0.07917983829975128,
      "Key": "N - N - N - N",
      "Unit": "\u00B0"
    },
    {
      "Value": -2.5612175464630127,
      "Key": "C - C - C - C",
      "Unit": "\u00B0"
    },
    {
      "Value": -3.069575786590576,
      "Key": "C - C - C - C",
      "Unit": "\u00B0"
    },
    {
      "Value": 1.5221960544586182,
      "Key": "C - C - C - C",
      "Unit": "\u00B0"
    },
    {
      "Value": -2.07356858253479,
      "Key": "C - C - C - C",
      "Unit": "\u00B0"
    },
    {
      "Value": -3.05572772026062,
      "Key": "C - N - N - C",
      "Unit": "\u00B0"
    },
    {
      "Value": 5.416545867919922,
      "Key": "C - N - N - C",
      "Unit": "\u00B0"
    },
    {
      "Value": 1.0227863788604736,
      "Key": "N - C - C - N",
      "Unit": "\u00B0"
    },
    {
      "Value": -0.11002416163682938,
      "Key": "N - C - C - N",
      "Unit": "\u00B0"
    },
    {
      "Value": 1.5956854820251465,
      "Key": "N - C - C - N",
      "Unit": "\u00B0"
    },
    {
      "Value": 1.096258521080017,
      "Key": "N - C - C - N",
      "Unit": "\u00B0"
    }
  ],
  "Angles": [
    {
      "Value": 90.1761245727539,
      "Key": "N - Ru - N",
      "Unit": "\u00B0"
    },
    {
      "Value": 90.0926742553711,
      "Key": "N - Ru - N",
      "Unit": "\u00B0"
    },
    {
      "Value": 127.57478332519531,
      "Key": "C - C - C",
      "Unit": "\u00B0"
    },
    {
      "Value": 128.2631072998047,
      "Key": "C - C - C",
      "Unit": "\u00B0"
    },
    {
      "Value": 128.1741485595703,
      "Key": "C - C - C",
      "Unit": "\u00B0"
    },
    {
      "Value": 127.826904296875,
      "Key": "C - C - C",
      "Unit": "\u00B0"
    }
  ],
  "Distances": [
    {
      "Value": 4.1148905754089355,
      "Key": "N - N",
      "Unit": "\u00C5"
    },
    {
      "Value": 4.116804599761963,
      "Key": "N - N",
      "Unit": "\u00C5"
    },
    {
      "Value": 2.054227828979492,
      "Key": "Ru - N",
      "Unit": "\u00C5"
    },
    {
      "Value": 2.0603229999542236,
      "Key": "Ru - N",
      "Unit": "\u00C5"
    },
    {
      "Value": 2.0636210441589355,
      "Key": "Ru - N",
      "Unit": "\u00C5"
    },
    {
      "Value": 2.0595943927764893,
      "Key": "Ru - N",
      "Unit": "\u00C5"
    }
  ],
  "PlaneDistances": [
    {
      "Value": 0.10349950194358826,
      "Key": "Ru - Mean Plane",
      "Unit": "\u00C5"
    },
    {
      "Value": -0.07903579622507095,
      "Key": "Ru - N4 Plane",
      "Unit": "\u00C5"
    }
  ],
  "Cavity": {
    "Value": 8.470042705535889,
    "Key": "Cavity size",
    "Unit": "\u00C5\u00B2"
  },
  "InterplanarAngle": {
    "Key": "[N1-Ru-N4]x[N2-Ru-N3]",
    "Value": 6.230171203613281,
    "Unit": "\u00B0"
  }
}