{
  "AnalysisType": "Porphyrin",
  "OutOfPlaneParameter": {
    "Key": "Doop (exp.)",
    "Value": 1.3801336847638084,
    "Unit": "\u00C5"
  },
  "Simulation": {
    "SimulationResult": [
      {
        "Key": "Doming",
        "Value": -0.0005707432351824338,
        "Unit": "\u00C5"
      },
      {
        "Key": "Saddling",
        "Value": -0.17597554780196048,
        "Unit": "\u00C5"
      },
      {
        "Key": "Ruffling",
        "Value": -1.434957535559472,
        "Unit": "\u00C5"
      },
      {
        "Key": "WavingX",
        "Value": 0.04482970879040577,
        "Unit": "\u00C5"
      },
      {
        "Key": "WavingY",
        "Value": 0.1421443293185006,
        "Unit": "\u00C5"
      },
      {
        "Key": "Propellering",
        "Value": 0.008001041018719846,
        "Unit": "\u00C5"
      },
      {
        "Key": "Doming2",
        "Value": 0.08222557839990685,
        "Unit": "\u00C5"
      },
      {
        "Key": "Saddling2",
        "Value": -0.032718862587052894,
        "Unit": "\u00C5"
      },
      {
        "Key": "Ruffling2",
        "Value": -0.03636274038096694,
        "Unit": "\u00C5"
      },
      {
        "Key": "WavingX2",
        "Value": -0.015027357370449274,
        "Unit": "\u00C5"
      },
      {
        "Key": "Propellering2",
        "Value": -0.005914855061729968,
        "Unit": "\u00C5"
      }
    ],
    "ConformationY": [
      0.5078176355576269,
      0.26333179553482505,
      0.06652198251490685,
      0.045548148269610414,
      -0.3094495618551231,
      -0.2780753308782796,
      -0.4383553921889198,
      -0.2103499682695018,
      -0.1405777115228757,
      0.042206046170228294,
      0.19293305084049214,
      0.2768204781699436,
      0.4485413861106803,
      0.26637093472265544,
      0.1623825211509168,
      0.0025692264136853164,
      -0.23799891449766786,
      -0.3041478994208064,
      -0.5263411486677873,
      -0.27966826270944334,
      -0.16140718238088791,
      0.016189962602959636,
      0.2649163092158241,
      0.3302217383706823,
      0.5078176355576269
    ],
    "OutOfPlaneParameter": {
      "Key": "Doop (sim.)",
      "Value": 1.3737043352975262,
      "Unit": "\u00C5"
    },
    "SimulationResultPercentage": [
      {
        "Key": "Doming",
        "Value": 0.02884394160227207,
        "Unit": " %"
      },
      {
        "Key": "Saddling",
        "Value": 8.893365897898263,
        "Unit": " %"
      },
      {
        "Key": "Ruffling",
        "Value": 72.51917991491867,
        "Unit": " %"
      },
      {
        "Key": "WavingX",
        "Value": 2.2655818285502902,
        "Unit": " %"
      },
      {
        "Key": "WavingY",
        "Value": 7.183620376413967,
        "Unit": " %"
      },
      {
        "Key": "Propellering",
        "Value": 0.4043526855426872,
        "Unit": " %"
      },
      {
        "Key": "Doming2",
        "Value": 4.155475939757494,
        "Unit": " %"
      },
      {
        "Key": "Saddling2",
        "Value": 1.6535298249344264,
        "Unit": " %"
      },
      {
        "Key": "Ruffling2",
        "Value": 1.8376823331281982,
        "Unit": " %"
      },
      {
        "Key": "WavingX2",
        "Value": 0.7594452140832876,
        "Unit": " %"
      },
      {
        "Key": "Propellering2",
        "Value": 0.2989220431704443,
        "Unit": " %"
      }
    ]
  },
  "Dihedrals": [
    {
      "Value": -0.2161499410867691,
      "Key": "N - N - N - N",
      "Unit": "\u00B0"
    },
    {
      "Value": 5.612282752990723,
      "Key": "C - C - C - C",
      "Unit": "\u00B0"
    },
    {
      "Value": -15.753129005432129,
      "Key": "C - C - C - C",
      "Unit": "\u00B0"
    },
    {
      "Value": 2.707801342010498,
      "Key": "C - C - C - C",
      "Unit": "\u00B0"
    },
    {
      "Value": 13.13472843170166,
      "Key": "C - C - C - C",
      "Unit": "\u00B0"
    },
    {
      "Value": 36.509891510009766,
      "Key": "C - N - N - C",
      "Unit": "\u00B0"
    },
    {
      "Value": -23.25794219970703,
      "Key": "C - N - N - C",
      "Unit": "\u00B0"
    },
    {
      "Value": 2.851001262664795,
      "Key": "N - C - C - N",
      "Unit": "\u00B0"
    },
    {
      "Value": -4.94919490814209,
      "Key": "N - C - C - N",
      "Unit": "\u00B0"
    },
    {
      "Value": 0.7614296674728394,
      "Key": "N - C - C - N",
      "Unit": "\u00B0"
    },
    {
      "Value": 1.3036906719207764,
      "Key": "N - C - C - N",
      "Unit": "\u00B0"
    }
  ],
  "Angles": [
    {
      "Value": 89.87133026123047,
      "Key": "N - Si - N",
      "Unit": "\u00B0"
    },
    {
      "Value": 90.50023651123047,
      "Key": "N - Si - N",
      "Unit": "\u00B0"
    },
    {
      "Value": 121.73009490966797,
      "Key": "C - C - C",
      "Unit": "\u00B0"
    },
    {
      "Value": 123.33267974853516,
      "Key": "C - C - C",
      "Unit": "\u00B0"
    },
    {
      "Value": 122.63308715820312,
      "Key": "C - C - C",
      "Unit": "\u00B0"
    },
    {
      "Value": 122.590576171875,
      "Key": "C - C - C",
      "Unit": "\u00B0"
    }
  ],
  "Distances": [
    {
      "Value": 3.940223217010498,
      "Key": "N - N",
      "Unit": "\u00C5"
    },
    {
      "Value": 3.940868616104126,
      "Key": "N - N",
      "Unit": "\u00C5"
    },
    {
      "Value": 1.976758360862732,
      "Key": "Si - N",
      "Unit": "\u00C5"
    },
    {
      "Value": 1.9711018800735474,
      "Key": "Si - N",
      "Unit": "\u00C5"
    },
    {
      "Value": 1.9634782075881958,
      "Key": "Si - N",
      "Unit": "\u00C5"
    },
    {
      "Value": 1.969890832901001,
      "Key": "Si - N",
      "Unit": "\u00C5"
    }
  ],
  "PlaneDistances": [
    {
      "Value": 0.02545134723186493,
      "Key": "Si - Mean Plane",
      "Unit": "\u00C5"
    },
    {
      "Value": 0.000313802738673985,
      "Key": "Si - N4 Plane",
      "Unit": "\u00C5"
    }
  ],
  "Cavity": {
    "Value": 7.763937473297119,
    "Key": "Cavity size",
    "Unit": "\u00C5\u00B2"
  },
  "InterplanarAngle": {
    "Key": "[N1-Si-N4]x[N2-Si-N3]",
    "Value": 0.217605859041214,
    "Unit": "\u00B0"
  }
}