{
  "AnalysisType": "Corrole",
  "OutOfPlaneParameter": {
    "Key": "Doop (exp.)",
    "Value": 0.7827549169277864,
    "Unit": "\u00C5"
  },
  "Simulation": {
    "SimulationResult": [
      {
        "Key": "Doming",
        "Value": -0.7468435434865591,
        "Unit": "\u00C5"
      },
      {
        "Key": "Saddling",
        "Value": -0.32794721412682437,
        "Unit": "\u00C5"
      },
      {
        "Key": "Ruffling",
        "Value": -0.2468245039240573,
        "Unit": "\u00C5"
      },
      {
        "Key": "WavingX",
        "Value": -0.06452960885137082,
        "Unit": "\u00C5"
      },
      {
        "Key": "WavingY",
        "Value": 0.012758348938777034,
        "Unit": "\u00C5"
      },
      {
        "Key": "Propellering",
        "Value": 0.02063872246153739,
        "Unit": "\u00C5"
      },
      {
        "Key": "Doming2",
        "Value": 0.08353212796145076,
        "Unit": "\u00C5"
      },
      {
        "Key": "Saddling2",
        "Value": -0.0013963454412224358,
        "Unit": "\u00C5"
      },
      {
        "Key": "Ruffling2",
        "Value": -0.04841657017271553,
        "Unit": "\u00C5"
      },
      {
        "Key": "WavingX2",
        "Value": 0.040725276254235596,
        "Unit": "\u00C5"
      },
      {
        "Key": "WavingY2",
        "Value": 0.006701253009080065,
        "Unit": "\u00C5"
      },
      {
        "Key": "Propellering2",
        "Value": 0.012135797060688652,
        "Unit": "\u00C5"
      }
    ],
    "ConformationY": [
      -0.07537621062535035,
      0.1325518153215512,
      -0.27474067373992606,
      0.07241660897677321,
      -0.14802762797549243,
      -0.1085291451679392,
      -0.05539560029511548,
      0.18092339437435065,
      -0.13779432236948583,
      0.2731499093442498,
      0.07360165270326696,
      0.08952635483777095,
      -0.011946890444304695,
      0.06036246482055166,
      -0.16210253158233628,
      -0.02309806237800823,
      -0.12501657303570998,
      -0.06544017442886897,
      -0.02294827483448026,
      0.33132257084062916,
      -0.2693900182925163,
      0.31077244214478994,
      -0.04482119420022682
    ],
    "OutOfPlaneParameter": {
      "Key": "Doop (sim.)",
      "Value": 0.782604976249657,
      "Unit": "\u00C5"
    },
    "SimulationResultPercentage": [
      {
        "Key": "Doming",
        "Value": 46.3173346332656,
        "Unit": " %"
      },
      {
        "Key": "Saddling",
        "Value": 20.338451060108415,
        "Unit": " %"
      },
      {
        "Key": "Ruffling",
        "Value": 15.30742716281658,
        "Unit": " %"
      },
      {
        "Key": "WavingX",
        "Value": 4.001962007958994,
        "Unit": " %"
      },
      {
        "Key": "WavingY",
        "Value": 0.7912403103956671,
        "Unit": " %"
      },
      {
        "Key": "Propellering",
        "Value": 1.2799610078858856,
        "Unit": " %"
      },
      {
        "Key": "Doming2",
        "Value": 5.180449850791148,
        "Unit": " %"
      },
      {
        "Key": "Saddling2",
        "Value": 0.08659778829017675,
        "Unit": " %"
      },
      {
        "Key": "Ruffling2",
        "Value": 3.002672383047802,
        "Unit": " %"
      },
      {
        "Key": "WavingX2",
        "Value": 2.5256779210993647,
        "Unit": " %"
      },
      {
        "Key": "WavingY2",
        "Value": 0.41559464601480534,
        "Unit": " %"
      },
      {
        "Key": "Propellering2",
        "Value": 0.7526312283255796,
        "Unit": " %"
      }
    ]
  },
  "Dihedrals": [
    {
      "Value": 0.6800518035888672,
      "Key": "N - N - N - N",
      "Unit": "\u00B0"
    },
    {
      "Value": 15.696197509765625,
      "Key": "C - C - C - C",
      "Unit": "\u00B0"
    },
    {
      "Value": 6.5503621101379395,
      "Key": "C - C - C - C",
      "Unit": "\u00B0"
    },
    {
      "Value": -22.34657096862793,
      "Key": "C - C - C - C",
      "Unit": "\u00B0"
    },
    {
      "Value": 3.8598122596740723,
      "Key": "C - C - C - C",
      "Unit": "\u00B0"
    },
    {
      "Value": 2.9203128814697266,
      "Key": "C - N - N - C",
      "Unit": "\u00B0"
    },
    {
      "Value": -6.42765998840332,
      "Key": "C - N - N - C",
      "Unit": "\u00B0"
    },
    {
      "Value": 1.358486294746399,
      "Key": "N - C - C - N",
      "Unit": "\u00B0"
    },
    {
      "Value": 1.9115397930145264,
      "Key": "N - C - C - N",
      "Unit": "\u00B0"
    },
    {
      "Value": -8.444085121154785,
      "Key": "N - C - C - N",
      "Unit": "\u00B0"
    },
    {
      "Value": 2.971773147583008,
      "Key": "N - C - C - N",
      "Unit": "\u00B0"
    }
  ],
  "Angles": [
    {
      "Value": 76.36894989013672,
      "Key": "N - Re - N",
      "Unit": "\u00B0"
    },
    {
      "Value": 88.03622436523438,
      "Key": "N - Re - N",
      "Unit": "\u00B0"
    },
    {
      "Value": 121.79737091064453,
      "Key": "C - C - C",
      "Unit": "\u00B0"
    },
    {
      "Value": 123.98641967773438,
      "Key": "C - C - C",
      "Unit": "\u00B0"
    },
    {
      "Value": 122.07754516601562,
      "Key": "C - C - C",
      "Unit": "\u00B0"
    }
  ],
  "Distances": [
    {
      "Value": 3.754260778427124,
      "Key": "N - N",
      "Unit": "\u00C5"
    },
    {
      "Value": 3.7514562606811523,
      "Key": "N - N",
      "Unit": "\u00C5"
    },
    {
      "Value": 2.006821870803833,
      "Key": "Re - N",
      "Unit": "\u00C5"
    },
    {
      "Value": 1.9985740184783936,
      "Key": "Re - N",
      "Unit": "\u00C5"
    },
    {
      "Value": 2.012136936187744,
      "Key": "Re - N",
      "Unit": "\u00C5"
    },
    {
      "Value": 2.0131003856658936,
      "Key": "Re - N",
      "Unit": "\u00C5"
    }
  ],
  "PlaneDistances": [
    {
      "Value": -0.913036584854126,
      "Key": "Re - Mean Plane",
      "Unit": "\u00C5"
    },
    {
      "Value": -0.7057446241378784,
      "Key": "Re - N4 Plane",
      "Unit": "\u00C5"
    }
  ],
  "Cavity": {
    "Value": 7.041673421859741,
    "Key": "Cavity size",
    "Unit": "\u00C5\u00B2"
  },
  "InterplanarAngle": {
    "Key": "[N1-Re-N4]x[N2-Re-N3]",
    "Value": 55.82488250732422,
    "Unit": "\u00B0"
  }
}